numcodecs_tokenize/__init__.py
numcodecs_tokenize/py.typed
numcodecs_tokenize/typing.py
numcodecs_tokenize-0.1.3.dist-info/METADATA
numcodecs_tokenize-0.1.3.dist-info/WHEEL
numcodecs_tokenize-0.1.3.dist-info/entry_points.txt
numcodecs_tokenize-0.1.3.dist-info/licenses/LICENSE
numcodecs_tokenize-0.1.3.dist-info/RECORD
